{
	"Leagues": {
		"NA Competitive": ["Majors", "Minors", "Novice"],
		"NA Tournaments": ["TPA"]
	},
	"Majors": {
		"Dallas": {
			"Arctag IceCaps": "MAIC",
			"Converse Ballstars": "MCBS",
			"Holdin' Gate Warriors": "MHGW",
			"Holy Handoff Grenades": "MHHG",
			"Iron Chef": "MICJ",
			"Los Ankeles Breakers": "MLAB",
			"Miami Ballphins": "MMIA",
			"Nuclear Jukes": "MNUK",
			"Okay Hens": "MOKN",
			"Veggie Tiles": "MVGT"
		}
	},
	"Minors": {
		"Blue": {
			"Arctag iceCaps": "NAIC",
			"Cap City in Blue": "NCCB",
			"Converse Ballstars": "NCBS",
			"Harlem Globebotters": "NHGB",
			"Returns of the Jedi": "NRTJ",
			"Scrim Reapers": "NSCR",
			"Stranger Pings": "NSRP"
		},
		"Red": {
			"Bottle Otters": "NBOT",
			"Iron Chef French": "NICF",
			"Land Before Timers": "NLBT",
			"Miami Ballphins": "NMIA",
			"Molotov Blocktails": "NMBT",
			"Nuclear Jukes": "NNUK",
			"Over the Pants Handoffs": "NOPH",
			"The Nights Watch": "NTNW"
		}
	},
	"Novice": {
		"Central": {
			"test": "hi"
		}
	}
}
